blend_env/__init__.py
blend_env/cli.py
blend_env/completion.py
blend_env/crypto.py
blend_env/export.py
blend_env/loader.py
blend_env/scaffold.py
blend_env-0.3.0.dist-info/licenses/LICENSE
blend_env-0.3.0.dist-info/METADATA
blend_env-0.3.0.dist-info/WHEEL
blend_env-0.3.0.dist-info/entry_points.txt
blend_env-0.3.0.dist-info/top_level.txt
blend_env-0.3.0.dist-info/RECORD
