Metadata-Version: 2.4
Name: blend-env
Version: 0.3.0
Summary: Blend global environment config with local .env files
Author-email: Thomas Weholt <thomas@weholt.org>
License: GPL-3.0-or-later
Requires-Python: >=3.11
License-File: LICENSE
Requires-Dist: python-dotenv>=1.0.1
Requires-Dist: typer>=0.9.0
Requires-Dist: rich>=13.7.0
Requires-Dist: cryptography>=42.0
Provides-Extra: dev
Requires-Dist: pytest>=8.3.5; extra == "dev"
Requires-Dist: pytest-cov>=5.0.0; extra == "dev"
Requires-Dist: ruff>=0.11.6; extra == "dev"
Requires-Dist: isort>=6.0.1; extra == "dev"
Requires-Dist: black>=25.1.0; extra == "dev"
Dynamic: license-file
